Workbook

Sheet Sheet1
A1: This is a JPM equity valuation, DDM and D&PDM, FY2020-25 historical and projection for 2026-30 (as of 11/04/2026-DD/MM/YYYY)
A2: How to read | B2: Contents | C2: Period | D2: Source | E2: Links
A3: =HYPERLINK("#'Income Statement'!A1", "Income Statement") -> Income Statement | B3: Company's Income statement | C3: FY 2020-25 | D3: K-10
A4: =HYPERLINK("#'Balance Sheet'!A1", "Balance Sheet") -> Balance Sheet | B4: Company’s Balance Sheet | C4: FY 2020-25 | D4: K-10
A5: =HYPERLINK("#'Key Metrics'!A1", "Key Metrics") -> Key Metrics | B5: Company's Key metrics | C5: FY 2020-25 | D5: K-10
A6: =HYPERLINK("#'Projections'!A20","Projections") -> Projections | B6: Future Projections based on Interest rate shift and Loan book shift "SEE E6" | C6: FY 2026-30 | D6: Past trends | E6: =HYPERLINK("#'Projections'!A1", "I.R.S.&L.B.S.") -> I.R.S.&L.B.S.
A7: =HYPERLINK("#'DDM, D&PDM Valuation'!L8", "DDM, D&PDM Valuation") -> DDM, D&PDM Valuation | B7: DDM and D&PDM (DDM with P/E exit multiple) valuation based on Projections and Assumptions "SEE E7" | C7: FY 2026-30 | D7: Projections | E7: =HYPERLINK("#'DDM, D&PDM Valuation'!A1","Assumptions") -> Assumptions
A13: How we came about the values
A14: =HYPERLINK("#'DDM, D&PDM Valuation'!A2", "Payout Ratio") -> Payout Ratio | B14: Calculated from the 10-K
A15: =HYPERLINK("#'DDM, D&PDM Valuation'!A3", "Cost of Equity") -> Cost of Equity | B15: Calculated from the 10-K
A16: =HYPERLINK("#'DDM, D&PDM Valuation'!A3", "EPS") -> EPS | B16: Derived from 10-K data, net income growth rate and share reduction with bear/base/bull cases
A17: =HYPERLINK("#'DDM, D&PDM Valuation'!A3", "Terminal Growth Rate") -> Terminal Growth Rate | B17: Conservative estimation based on inflation and GDP growth (11/04/2026)
A18: =HYPERLINK("#'DDM, D&PDM Valuation'!A3", "Share reduction") -> Share reduction | B18: Conservative estimation based on historical data and bear/base/bull cases
A19: =HYPERLINK("#'DDM, D&PDM Valuation'!A3", "Net income growth rate") -> Net income growth rate | B19: Estimated with bear/bull/base cases

Sheet Income Statement
A1: JPMorgan Chase & Co. — Consolidated Statements of Income
A2: $ in millions | Source: JPMorgan Chase 10-K Filings (SEC EDGAR)
A3: Year ended December 31, | B3: 2020 | C3: 2021 | D3: 2022 | E3: 2023 | F3: 2024 | G3: 2025
A4: REVENUE
A5: Investment banking fees | B5: 8476 | C5: 13216 | D5: 6686 | E5: 6519 | F5: 8910 | G5: 9841
A6: Principal transactions | B6: 13121 | C6: 16304 | D6: 19912 | E6: 24460 | F6: 24787 | G6: 28039
A7: Lending- and deposit-related fees | B7: 6815 | C7: 7032 | D7: 7098 | E7: 7413 | F7: 7606 | G7: 7781
A8: Asset management fees | B8: 13350 | C8: 14405 | D8: 14096 | E8: 15220 | F8: 17801 | G8: 19738
A9: Commissions and other fees | B9: 6340 | C9: 6624 | D9: 6581 | E9: 6836 | F9: 7530 | G9: 7914
A10: Investment securities gains/(losses) | B10: 347 | C10: -345 | D10: -2380 | E10: -3180 | F10: -1021 | G10: -309
A11: Mortgage fees and related income | B11: 3426 | C11: 2170 | D11: 1250 | E11: 1176 | F11: 1401 | G11: 1418
A12: Card income | B12: 5070 | C12: 5102 | D12: 4420 | E12: 4784 | F12: 5497 | G12: 5607
A13: Other income | B13: 4798 | C13: 4830 | D13: 4322 | E13: 5609 | F13: 12462 | G13: 6975
A14: Noninterest revenue | B14: =SUM(B5:B13) -> 61743 | C14: =SUM(C5:C13) -> 69338 | D14: =SUM(D5:D13) -> 61985 | E14: =SUM(E5:E13) -> 68837 | F14: =SUM(F5:F13) -> 84973 | G14: =SUM(G5:G13) -> 87004
A15: Interest income | B15: 68022 | C15: 57133 | D15: 92807 | E15: 170588 | F15: 193933 | G15: 211184
A16: Interest expense | B16: 12724 | C16: 4822 | D16: 26097 | E16: 81321 | F16: 101350 | G16: 115741
A17: Net interest income | B17: =B15-B16 -> 55298 | C17: =C15-C16 -> 52311 | D17: =D15-D16 -> 66710 | E17: =E15-E16 -> 89267 | F17: =F15-F16 -> 92583 | G17: =G15-G16 -> 95443
A18: TOTAL NET REVENUE | B18: 119543 | C18: 121649 | D18: 128695 | E18: 158104 | F18: 177556 | G18: 182447
A19: EXPENSES
A20: Provision for credit losses | B20: 17480 | C20: -9256 | D20: 6389 | E20: 9320 | F20: 10678 | G20: 14212
A21: Compensation expense | B21: 37499 | C21: 40388 | D21: 41636 | E21: 46465 | F21: 51357 | G21: 54234
A22: Occupancy expense | B22: 4355 | C22: 4262 | D22: 4696 | E22: 4590 | F22: 5026 | G22: 5251
A23: Technology, comm. & equipment | B23: 9028 | C23: 9116 | D23: 9358 | E23: 9246 | F23: 9831 | G23: 10456
A24: Professional and outside services | B24: 7697 | C24: 8140 | D24: 9012 | E24: 10235 | F24: 11057 | G24: 11384
A25: Marketing | B25: 2780 | C25: 3302 | D25: 3250 | E25: 3355 | F25: 3791 | G25: 3943
A26: Other expense | B26: 5297 | C26: 6135 | D26: 8188 | E26: 13281 | F26: 10735 | G26: 10372
A27: TOTAL NONINTEREST EXPENSE | B27: 66656 | C27: 71343 | D27: 76140 | E27: 87172 | F27: 91797 | G27: 95640
A28: PRE-PROVISION PROFIT | B28: =B18-B20 -> 102063 | C28: =C18-C20 -> 130905 | D28: =D18-D20 -> 122306 | E28: =E18-E20 -> 148784 | F28: =F18-F20 -> 166878 | G28: =G18-G20 -> 168235
A29: Income before income tax | B29: =B28-B27+B20 -> 52887 | C29: =C28-C27+C20 -> 50306 | D29: =D28-D27+D20 -> 52555 | E29: =E28-E27+E20 -> 70932 | F29: =F28-F27+F20 -> 85759 | G29: =G28-G27+G20 -> 86807
A30: Income tax expense | B30: 5640 | C30: 6032 | D30: 6671 | E30: 8490 | F30: 10756 | G30: 11027
A31: NET INCOME | B31: 29131 | C31: 48334 | D31: 37676 | E31: 49552 | F31: 58471 | G31: 57048
A32: PER SHARE DATA
A33: Diluted EPS ($) | B33: 8.88 | C33: 15.36 | D33: 12.09 | E33: 16.23 | F33: 19.75 | G33: 20.02
A34: Book value per share ($) | B34: 81.75 | C34: 88.07 | D34: 90.29 | E34: 104.45 | F34: 116.07 | G34: 126.99
A35: Tangible book value per share ($) | B35: 66.11 | C35: 71.53 | D35: 73.12 | E35: 86.08 | F35: 97.3 | G35: 107.56
A37: Source: JPMorgan Chase & Co. Annual Report on Form 10-K, FY2020–FY2025, SEC EDGAR
A38: Color code: Blue = hardcoded input from 10-K | Black = formula | Green = cross-sheet link

Sheet Balance Sheet
A1: JPMorgan Chase & Co. — Selected Balance Sheet Data
A2: $ in millions | Source: JPMorgan Chase 10-K Filings (SEC EDGAR)
A3: Balance Sheet Item | B3: 2020 | C3: 2021 | D3: 2022 | E3: 2023 | F3: 2024 | G3: 2025
A4: ASSETS
A5: Cash & deposits with banks | B5: 666747 | C5: 728730 | D5: 683936 | E5: 624151 | F5: 469317 | G5: 520498
A6: Investment securities (net) | B6: 606383 | C6: 635064 | D6: 538834 | E6: 571552 | F6: 681320 | G6: 702891
A7: Total loans | B7: 1011882 | C7: 1077714 | D7: 1135647 | E7: 1323706 | F7: 1347988 | G7: 1402311
A8: Allowance for loan losses | B8: -19044 | C8: -16383 | D8: -17740 | E8: -22420 | F8: -24345 | G8: -26890
A9: Loans net of allowance | B9: 992838 | C9: 1061331 | D9: 1117907 | E9: 1301286 | F9: 1323643 | G9: 1375421
A10: Trading assets | B10: 491728 | C10: 478547 | D10: 482963 | E10: 540607 | F10: 637784 | G10: 681234
A11: Total assets | B11: 3384757 | C11: 3743567 | D11: 3665743 | E11: 3875393 | F11: 4000272 | G11: 4187248
A12: LIABILITIES
A13: Total deposits | B13: 2242093 | C13: 2462303 | D13: 2340179 | E13: 2395907 | F13: 2401637 | G13: 2496781
A14: Short-term borrowings | B14: 248083 | C14: 218456 | D14: 328081 | E14: 427547 | F14: 381956 | G14: 398234
A15: Long-term debt | B15: 297473 | C15: 294908 | D15: 296927 | E15: 302404 | F15: 340614 | G15: 371289
A16: Total liabilities | B16: 3126627 | C16: 3453282 | D16: 3379726 | E16: 3574148 | F16: 3698372 | G16: 3872541
A17: EQUITY
A18: Total stockholders equity | B18: 258225 | C18: 290285 | D18: 285747 | E18: 301245 | F18: 301900 | G18: 314707
A19: Common shares outstanding (mm) | B19: 3085 | C19: 3058 | D19: 2933 | E19: 2904 | F19: 2862 | G19: 2839
A20: LOAN PORTFOLIO MIX
A21: Consumer loans (excl. card) | B21: 458389 | C21: 462098 | D21: 463765 | E21: 410093 | F21: 392810 | G21: 381234
A22: Credit card loans | B22: 157278 | C22: 170268 | D22: 181019 | E22: 211123 | F22: 232860 | G22: 249832
A23: Wholesale loans | B23: 396215 | C23: 445348 | D23: 490863 | E23: 702490 | F23: 722318 | G23: 771245
A24: CREDIT QUALITY
A25: Allowance for loan losses ($mm) | B25: 19044 | C25: 16383 | D25: 17740 | E25: 22420 | F25: 24345 | G25: 26890
A26: ACL / Total loans ratio | B26: =B25/B7 -> 0.018820376 | C26: =C25/C7 -> 0.015201621 | D26: =D25/D7 -> 0.015621051 | E26: =E25/E7 -> 0.016937296 | F26: =F25/F7 -> 0.01806025 | G26: =G25/G7 -> 0.01917549
A27: Net charge-offs ($mm) | B27: 5572 | C27: 2904 | D27: 2895 | E27: 6374 | F27: 8638 | G27: 10934
A28: NCO ratio (NCO / Avg loans) | B28: =B27/B7 -> 0.0055065709 | C28: =C27/C7 -> 0.0026945924 | D28: =D27/D7 -> 0.0025492076 | E28: =E27/E7 -> 0.0048152686 | F28: =F27/F7 -> 0.0064080689 | G28: =G27/G7 -> 0.0077971292
A30: Source: JPMorgan Chase & Co. Annual Report on Form 10-K, FY2020–FY2025, SEC EDGAR
A31: Note: Some balance sheet line items are rounded or estimated from reported segment data where consolidated detail was unavailable.

Sheet Key Metrics
A1: JPMorgan Chase & Co. — Key Financial Metrics & Ratios
A2: $ in millions unless noted | Source: JPMorgan Chase 10-K Filings (SEC EDGAR)
A3: Metric | B3: 2020 | C3: 2021 | D3: 2022 | E3: 2023 | F3: 2024 | G3: 2025
A4: PROFITABILITY
A5: Return on Common Equity (ROE) | B5: 0.12 | C5: 0.19 | D5: 0.14 | E5: 0.17 | F5: 0.18 | G5: 0.17
A6: Return on Tangible Common Eq (ROTCE) | B6: 0.14 | C6: 0.23 | D6: 0.18 | E6: 0.21 | F6: 0.22 | G6: 0.2
A7: Net Income ($mm) | B7: ='Income Statement'!B31 -> 29131 | C7: ='Income Statement'!C31 -> 48334 | D7: ='Income Statement'!D31 -> 37676 | E7: ='Income Statement'!E31 -> 49552 | F7: ='Income Statement'!F31 -> 58471 | G7: ='Income Statement'!G31 -> 57048
A8: Total Net Revenue ($mm) | B8: ='Income Statement'!B18 -> 119543 | C8: ='Income Statement'!C18 -> 121649 | D8: ='Income Statement'!D18 -> 128695 | E8: ='Income Statement'!E18 -> 158104 | F8: ='Income Statement'!F18 -> 177556 | G8: ='Income Statement'!G18 -> 182447
A9: Net Income Margin | B9: ='Income Statement'!B31/'Income Statement'!B18 -> 0.24368637 | C9: ='Income Statement'!C31/'Income Statement'!C18 -> 0.39732345 | D9: ='Income Statement'!D31/'Income Statement'!D18 -> 0.29275419 | E9: ='Income Statement'!E31/'Income Statement'!E18 -> 0.31341396 | F9: ='Income Statement'!F31/'Income Statement'!F18 -> 0.32931019 | G9: ='Income Statement'!G31/'Income Statement'!G18 -> 0.31268259
A10: Pre-Provision Profit ($mm) | B10: ='Income Statement'!B28 -> 102063 | C10: ='Income Statement'!C28 -> 130905 | D10: ='Income Statement'!D28 -> 122306 | E10: ='Income Statement'!E28 -> 148784 | F10: ='Income Statement'!F28 -> 166878 | G10: ='Income Statement'!G28 -> 168235
A11: CAPITAL ADEQUACY
A12: CET1 Capital Ratio | B12: 0.131 | C12: 0.131 | D12: 0.132 | E12: 0.15 | F12: 0.157 | G12: 0.146
A13: Tier 1 Capital Ratio | B13: 0.15 | C13: 0.15 | D13: 0.149 | E13: 0.166 | F13: 0.168 | G13: 0.155
A14: Total Capital Ratio | B14: 0.173 | C14: 0.168 | D14: 0.168 | E14: 0.185 | F14: 0.185 | G14: 0.174
A15: CREDIT QUALITY
A16: Provision for Credit Losses ($mm) | B16: ='Income Statement'!B20 -> 17480 | C16: ='Income Statement'!C20 -> -9256 | D16: ='Income Statement'!D20 -> 6389 | E16: ='Income Statement'!E20 -> 9320 | F16: ='Income Statement'!F20 -> 10678 | G16: ='Income Statement'!G20 -> 14212
A17: Provision as % of Revenue | B17: ='Income Statement'!B20/'Income Statement'!B18 -> 0.14622353 | C17: ='Income Statement'!C20/'Income Statement'!C18 -> -0.076087761 | D17: ='Income Statement'!D20/'Income Statement'!D18 -> 0.049644508 | E17: ='Income Statement'!E20/'Income Statement'!E18 -> 0.05894854 | F17: ='Income Statement'!F20/'Income Statement'!F18 -> 0.060138773 | G17: ='Income Statement'!G20/'Income Statement'!G18 -> 0.077896595
A18: EFFICIENCY
A19: Efficiency Ratio | B19: ='Income Statement'!B27/'Income Statement'!B18 -> 0.55759016 | C19: ='Income Statement'!C27/'Income Statement'!C18 -> 0.58646598 | D19: ='Income Statement'!D27/'Income Statement'!D18 -> 0.59163138 | E19: ='Income Statement'!E27/'Income Statement'!E18 -> 0.5513586 | F19: ='Income Statement'!F27/'Income Statement'!F18 -> 0.51700309 | G19: ='Income Statement'!G27/'Income Statement'!G18 -> 0.52420703
A20: Noninterest Expense ($mm) | B20: ='Income Statement'!B27 -> 66656 | C20: ='Income Statement'!C27 -> 71343 | D20: ='Income Statement'!D27 -> 76140 | E20: ='Income Statement'!E27 -> 87172 | F20: ='Income Statement'!F27 -> 91797 | G20: ='Income Statement'!G27 -> 95640
A21: REVENUE MIX
A22: Net Interest Income ($mm) | B22: ='Income Statement'!B17 -> 55298 | C22: ='Income Statement'!C17 -> 52311 | D22: ='Income Statement'!D17 -> 66710 | E22: ='Income Statement'!E17 -> 89267 | F22: ='Income Statement'!F17 -> 92583 | G22: ='Income Statement'!G17 -> 95443
A23: Noninterest Revenue ($mm) | B23: ='Income Statement'!B14 -> 61743 | C23: ='Income Statement'!C14 -> 69338 | D23: ='Income Statement'!D14 -> 61985 | E23: ='Income Statement'!E14 -> 68837 | F23: ='Income Statement'!F14 -> 84973 | G23: ='Income Statement'!G14 -> 87004
A24: NII as % of Total Revenue | B24: ='Income Statement'!B17/'Income Statement'!B18 -> 0.46257832 | C24: ='Income Statement'!C17/'Income Statement'!C18 -> 0.43001587 | D24: ='Income Statement'!D17/'Income Statement'!D18 -> 0.51835736 | E24: ='Income Statement'!E17/'Income Statement'!E18 -> 0.56460937 | F24: ='Income Statement'!F17/'Income Statement'!F18 -> 0.52142986 | G24: ='Income Statement'!G17/'Income Statement'!G18 -> 0.52312726
A25: GROWTH (YoY)
A26: Revenue Growth | B26: - | C26: =('Income Statement'!C18-'Income Statement'!B18)/'Income Statement'!B18 -> 0.017617092 | D26: =('Income Statement'!D18-'Income Statement'!C18)/'Income Statement'!C18 -> 0.057920739 | E26: =('Income Statement'!E18-'Income Statement'!D18)/'Income Statement'!D18 -> 0.22851704 | F26: =('Income Statement'!F18-'Income Statement'!E18)/'Income Statement'!E18 -> 0.12303294 | G26: =('Income Statement'!G18-'Income Statement'!F18)/'Income Statement'!F18 -> 0.027546239
A27: Net Income Growth | B27: - | C27: =('Income Statement'!C31-'Income Statement'!B31)/'Income Statement'!B31 -> 0.65919467 | D27: =('Income Statement'!D31-'Income Statement'!C31)/'Income Statement'!C31 -> -0.2205073 | E27: =('Income Statement'!E31-'Income Statement'!D31)/'Income Statement'!D31 -> 0.31521393 | F27: =('Income Statement'!F31-'Income Statement'!E31)/'Income Statement'!E31 -> 0.17999273 | G27: =('Income Statement'!G31-'Income Statement'!F31)/'Income Statement'!F31 -> -0.024336851
A28: EPS Growth | B28: - | C28: =('Income Statement'!C33-'Income Statement'!B33)/'Income Statement'!B33 -> 0.72972973 | D28: =('Income Statement'!D33-'Income Statement'!C33)/'Income Statement'!C33 -> -0.21289062 | E28: =('Income Statement'!E33-'Income Statement'!D33)/'Income Statement'!D33 -> 0.34243176 | F28: =('Income Statement'!F33-'Income Statement'!E33)/'Income Statement'!E33 -> 0.21688232 | G28: =('Income Statement'!G33-'Income Statement'!F33)/'Income Statement'!F33 -> 0.013670886
A29: PER SHARE
A30: Diluted EPS ($) | B30: ='Income Statement'!B33 -> 8.88 | C30: ='Income Statement'!C33 -> 15.36 | D30: ='Income Statement'!D33 -> 12.09 | E30: ='Income Statement'!E33 -> 16.23 | F30: ='Income Statement'!F33 -> 19.75 | G30: ='Income Statement'!G33 -> 20.02
A31: Book Value per Share ($) | B31: ='Income Statement'!B34 -> 81.75 | C31: ='Income Statement'!C34 -> 88.07 | D31: ='Income Statement'!D34 -> 90.29 | E31: ='Income Statement'!E34 -> 104.45 | F31: ='Income Statement'!F34 -> 116.07 | G31: ='Income Statement'!G34 -> 126.99
A32: Tangible Book Value per Share ($) | B32: ='Income Statement'!B35 -> 66.11 | C32: ='Income Statement'!C35 -> 71.53 | D32: ='Income Statement'!D35 -> 73.12 | E32: ='Income Statement'!E35 -> 86.08 | F32: ='Income Statement'!F35 -> 97.3 | G32: ='Income Statement'!G35 -> 107.56
A34: Source: JPMorgan Chase & Co. Annual Report on Form 10-K, FY2020–FY2025, SEC EDGAR
A35: Color code: Blue = hardcoded input | Black = formula | Green = cross-sheet link from Income Statement

Sheet Projections
A1: Net Interest Income 2026
A2: Scenario Summary | B2: Bear | C2: Base | D2: Bull
A3: Interest rate shift | B3: -150 | C3: -75 | D3: -25
A4: Loan Book shift | B4: 0.01 | C4: 0.03 | D4: 0.05
A5: NII 2026 | B5: 94951.469 | C5: 97568.993 | D5: 99964.612
A8: NII Projections 2026-2030
A11: Assumptions | B11: 2026 | C11: 2027 | D11: 2028 | E11: 2029 | F11: 2030
A12: Bear loan growth | B12: 0.01 | C12: 0.01 | D12: 0.01 | E12: 0.01 | F12: 0.01
A13: Bear rate shift | B13: -0.015 | C13: -0.005 | D13: -0.0025 | E13: -0.005 | F13: -0.005
A14: Base loan growth | B14: 0.03 | C14: 0.03 | D14: 0.03 | E14: 0.03 | F14: 0.03
A15: Base rate shift | B15: -0.0075 | C15: -0.0025 | D15: 0.0025 | E15: 0.005 | F15: 0.005
A16: Bull loan growth | B16: 0.05 | C16: 0.05 | D16: 0.05 | E16: 0.05 | F16: 0.05
A17: Bull rate shift | B17: -0.0025 | C17: 0 | D17: 0.0025 | E17: 0.01 | F17: 0.012
A20: Scenario Summary | B20: 2026 | C20: 2027 | D20: 2028 | E20: 2029 | F20: 2030 | G20: NII growth
A21: Bear | B21: =95443*(1+B12)*(1+B13) -> 94951.469 | C21: =B21*(1+C12)*(1+C13) -> 95421.478 | D21: =C21*(1+D12)*(1+D13) -> 96134.754 | E21: =D21*(1+E12)*(1+E13) -> 96610.621 | F21: =E21*(1+F12)*(1+F13) -> 97088.843 | G21: =_xlfn.RRI(5,B21,F21) -> 0.0044620389
A22: Base | B22: =95443*(1+B14)*(1+B15) -> 97568.993 | C22: =B22*(1+C14)*(1+C15) -> 100244.82 | D22: =C22*(1+D14)*(1+D15) -> 103510.3 | E22: =D22*(1+E14)*(1+E15) -> 107148.68 | F22: =E22*(1+F14)*(1+F15) -> 110914.96 | G22: =_xlfn.RRI(5,B22,F22) -> 0.025972362
A23: Bull | B23: =95443*(1+B16)*(1+B17) -> 99964.612 | C23: =B23*(1+C16)*(1+C17) -> 104962.84 | D23: =C23*(1+D16)*(1+D17) -> 110486.51 | E23: =D23*(1+E16)*(1+E17) -> 117170.95 | F23: =E23*(1+F16)*(1+F17) -> 124505.85 | G23: =_xlfn.RRI(5,B23,F23) -> 0.044885477

Sheet DDM, D&PDM Valuation
A1: Assumptions
A2: Payout Ratio | B2: 0.27
A3: Cost of Equity | B3: 0.1055
A4: Terminal Growth Rate | B4: 0.03
A5: Net income growth rate | B5: 0.042
A6: Share reduction | B6: 0.01
A7: P/E multiple
A8: Bear | B8: 10.5 | L8: Valuation Result Table
A9: Base | B9: 13.5 | L9: Model | M9: Bear | N9: Base | O9: Bull
A10: Bull | B10: 16.5 | L10: DDM | M10: =B23 -> 63.106843 | N10: =B16 -> 70.649256 | O10: =B30 -> 79.942837
A11: Projections 2026-30 | B11: Base | C11: =HYPERLINK("#'DDM, D&PDM Valuation'!A32", "EPS growth") -> EPS growth | D11: =Projections!G22 -> 0.025972362 | E11: Share reduction | G11: 0.01 | L11: D&PDM | M11: =B24 -> 154.22923 | N11: =B17 -> 218.02004 | O11: =B31 -> 299.93423
A12: 20.02 | B12: 2026 | C12: 2027 | D12: 2028 | E12: 2029 | F12: 2030 | L12: Current Market Price | M12: 288 | N12: 288 | O12: 288
A13: EPS | B13: =(20.02*(1+$D$11))/(1-$G$11) -> 20.747441 | C13: =(B13*(1+$D$11))/(1-$G$11) -> 21.501314 | D13: =(C13*(1+$D$11))/(1-$G$11) -> 22.28258 | E13: =(D13*(1+$D$11))/(1-$G$11) -> 23.092234 | F13: =(E13*(1+$D$11))/(1-$G$11) -> 23.931306
A14: Dividend | B14: =B13*$B$2 -> 5.6018091 | C14: =C13*$B$2 -> 5.8053549 | D14: =D13*$B$2 -> 6.0162966 | E14: =E13*$B$2 -> 6.2349031 | F14: =F13*$B$2 -> 6.4614527 | L14: Refrence Table
A15: Discounted Divident | B15: =B14/((1+$B$3))^1 -> 5.0672176 | C15: =C14/((1+$B$3))^2 -> 4.7501932 | D15: =D14/((1+$B$3))^3 -> 4.4530031 | E15: =E14/((1+$B$3))^4 -> 4.1744063 | F15: =F14/((1+$B$3))^5 -> 3.9132396 | L15: Payout Ratio | M15: 0.27
A16: DDM | B16: =SUM(B15:F15)+((F14*(1+B4)/(B3-B4))*(1/(1+B3)^6)) -> 70.649256 | L16: Cost of Equity | M16: 0.1055
A17: D&PDM | B17: =SUM(B15:E15)+(F14+F13*B9)/(1+B3)^5 -> 218.02004 | L17: Terminal Growth Rate | M17: 0.03
A18: Projections 2026-30 | B18: Bear | C18: =HYPERLINK("#'DDM, D&PDM Valuation'!A32", "EPS growth") -> EPS growth | D18: =Projections!G21 -> 0.0044620389 | E18: Share reduction | G18: 0.005 | M18: Bear | N18: Base | O18: Bull
A19: 20.02 | B19: 2026 | C19: 2027 | D19: 2028 | E19: 2029 | F19: 2030 | L19: EPS Growth Rates | M19: 0.005 | N19: 0.042 | O19: 0.056
A20: EPS | B20: =(20.02*(1+$D$18))/(1-$G$18) -> 20.210382 | C20: =(B20*(1+$D$18))/(1-$G$18) -> 20.402574 | D20: =(C20*(1+$D$18))/(1-$G$18) -> 20.596594 | E20: =(D20*(1+$D$18))/(1-$G$18) -> 20.792459 | F20: =(E20*(1+$D$18))/(1-$G$18) -> 20.990187 | L20: Share reduction | M20: =G11 -> 0.01 | N20: =G18 -> 0.005 | O20: =G25 -> 0.02
A21: Dividend | B21: =B20*$B$2 -> 5.4568031 | C21: =C20*$B$2 -> 5.5086951 | D21: =D20*$B$2 -> 5.5610805 | E21: =E20*$B$2 -> 5.6139641 | F21: =F20*$B$2 -> 5.6673505
A22: Discounted Divident | B22: =B21/((1+$B$3)^1) -> 4.9360499 | C22: =C21/((1+$B$3)^2) -> 4.5074533 | D22: =D21/((1+$B$3)^3) -> 4.1160718 | E22: =E21/((1+$B$3)^4) -> 3.7586738 | F22: =F21/((1+$B$3)^5) -> 3.4323087
A23: DDM | B23: =SUM(B22:F22)+((F21*(1+B4)/(B3-B4))*(1/(1+B3)^6)) -> 63.106843
A24: D&PDM | B24: =SUM(B22:E22)+(F21+F20*B8)/(1+B3)^5 -> 154.22923
A25: Projections 2026-30 | B25: Bull | C25: =HYPERLINK("#'DDM, D&PDM Valuation'!A32", "EPS growth") -> EPS growth | D25: =Projections!G23 -> 0.044885477 | E25: Share reduction | G25: 0.02
A26: 20.02 | B26: 2026 | C26: 2027 | D26: 2028 | E26: 2029 | F26: 2030
A27: EPS | B27: =(20.02*(1+$D$25))/(1-$G$25) -> 21.345518 | C27: =(B27*(1+$D$25))/(1-$G$25) -> 22.758797 | D27: =(C27*(1+$D$25))/(1-$G$25) -> 24.26565 | E27: =(D27*(1+$D$25))/(1-$G$25) -> 25.87227 | F27: =(E27*(1+$D$25))/(1-$G$25) -> 27.585265
A28: Dividend | B28: =B27*$B$2 -> 5.7632898 | C28: =C27*$B$2 -> 6.1448753 | D28: =D27*$B$2 -> 6.5517254 | E28: =E27*$B$2 -> 6.985513 | F28: =F27*$B$2 -> 7.4480215
A29: Discounted Dividend | B29: =B28/((1+$B$3)^1) -> 5.2132879 | C29: =C28/((1+$B$3)^2) -> 5.0280036 | D29: =D28/((1+$B$3)^3) -> 4.8493044 | E29: =E28/((1+$B$3)^4) -> 4.6769564 | F29: =F28/((1+$B$3)^5) -> 4.5107337
A30: DDM | B30: =SUM(B29:F29)+((F28*(1+B4)/(B3-B4))*(1/(1+B3)^6)) -> 79.942837
A31: D&PDM | B31: =SUM(B29:E29)+(F28+F27*B10)/(1+B3)^5 -> 299.93423
A34: "SEE ME"
A35: EPS growth is proxied by projected NII growth (Bear/Base/Bull), per Projections tab
